{
  "identity": {
    "id": "7b8fba68-798f-40e2-a66d-c2a95ce47160",
    "name": "ContactType",
    "description": "Contact type enumerator. Contact type specify what part of organization you contact."
  },
  "version": {
    "major": 1,
    "minor": 3,
    "revision": 0
  },
  "object": {
    "parent": {
      "id": "277d8d52-77ca-4bac-951d-c08509aa12bf",
      "name": "/organizations/Infort Technologies/systems/Client/applications/User"
    },
    "picture": "",
    "tags": [],
    "documents": [],
    "contact": {
      "identity": {}
    },
    "type": "DataSet",
    "usage": "Enum",
    "access": "External",
    "properties": [],
    "elements": [{"identity":{"name":"default"},"links":[],"frame":{"position":{"left":789,"top":28,"width":0,"height":0}},"style":{"border":{"left":{"color":"#FFC107"}}}}],
    "history": {
      "created": "2018-10-07T22:26:06.66",
      "createdBy": "sashaberger@hotmail.com",
      "updated": "2018-10-07T22:38:58.18",
      "updatedBy": "sashaberger@hotmail.com",
      "mirrored": "2018-10-07T07:59:33.427",
      "completions": [
        {
          "status": "Finalized",
          "completed": "2018-10-07T22:26:19.167",
          "completedBy": "sashaberger@hotmail.com",
          "completedByMessage": "/organizations/Infort Technologies/systems/Client/applications/User/interfaces/Persons/issues/3383/messages/23"
        },
        {
          "status": "Approved",
          "completed": "2018-10-07T22:38:57.993",
          "completedBy": "sashaberger@hotmail.com",
          "completedByMessage": "/organizations/Infort Technologies/systems/Client/applications/User/interfaces/Persons/issues/3383/messages/23"
        }
      ]
    },
    "lastApprovedVersion": {
      "major": 1,
      "minor": 3,
      "revision": 0
    }
  },
  "external": true,
  "structure": {
    "fields": [
      {
        "identity": {
          "id": "046225f9-dead-4da1-b942-91f48ce931c9",
          "name": "Code",
          "description": "The code (used as the code in the resource instance). If the code is in italics, this indicates that the code is not selectable ('Abstract')\n"
        },
        "order": 1,
        "usage": "Value",
        "count": 1,
        "type": "String",
        "size": 16,
        "optional": true,
        "value": "",
        "format": "",
        "access": 255,
        "privacy": "low"
      },
      {
        "identity": {
          "id": "36ef0eb9-81d2-408e-b9bf-26e94b7ba4eb",
          "name": "Display",
          "description": "The display (used in the display element of a Coding). If there is no display, implementers should not simply display the code, but map the concept into their application"
        },
        "order": 2,
        "usage": "Name",
        "type": "String",
        "size": 16,
        "optional": true,
        "access": 255,
        "privacy": "low"
      },
      {
        "identity": {
          "id": "78422373-20a8-4ef8-8d98-039cffa00c1c",
          "name": "Definition",
          "description": "An explanation of the meaning of the concept"
        },
        "order": 3,
        "usage": "Description",
        "type": "String",
        "size": 0,
        "optional": true,
        "access": 255,
        "privacy": "low"
      }
    ],
    "keys": []
  },
  "layouts": [],
  "data": {
    "records": [
      {
        "index": 1,
        "values": [
          "ORG",
          "Organization",
          "Contact details for organization general information or head quaters information."
        ]
      },
      {
        "index": 2,
        "values": [
          "BILL",
          "Billing",
          "Contact details for information regarding to billing/general finance enquiries."
        ]
      },
      {
        "index": 3,
        "values": [
          "ADMIN",
          "Administrative",
          "Contact details for administrative enquiries."
        ]
      },
      {
        "index": 4,
        "values": [
          "HR",
          "Human Resource",
          "Contact details for issues related to Human Resources, such as staff matters, OH&S etc."
        ]
      },
      {
        "index": 5,
        "values": [
          "PAYOR",
          "Payor",
          "Contact details for dealing with issues related to insurance claims/adjudication/payment."
        ]
      },
      {
        "index": 6,
        "values": [
          "PATINF",
          "Patient",
          "Generic information contact for patients."
        ]
      },
      {
        "index": 7,
        "values": [
          "PRESS",
          "Press",
          "Dedicated contact point for matters relating to press enquiries. "
        ]
      }
    ],
    "examples": []
  }
}